rtoml-0.13.0.dist-info/METADATA
rtoml-0.13.0.dist-info/WHEEL
rtoml-0.13.0.dist-info/licenses/LICENSE
rtoml/__init__.py
rtoml/_rtoml.cpython-312-arm-linux-gnueabihf.so
rtoml/_rtoml.pyi
rtoml/py.typed
rtoml-0.13.0.dist-info/RECORD
