Metadata-Version: 2.4
Name: rtoml
Version: 0.13.0
Classifier: Development Status :: 5 - Production/Stable
Classifier: Programming Language :: Python
Classifier: Programming Language :: Python :: 3
Classifier: Programming Language :: Python :: 3 :: Only
Classifier: Programming Language :: Python :: 3.10
Classifier: Programming Language :: Python :: 3.11
Classifier: Programming Language :: Python :: 3.12
Classifier: Programming Language :: Python :: 3.13
Classifier: Programming Language :: Python :: 3.14
Classifier: Intended Audience :: Developers
Classifier: Intended Audience :: Information Technology
Classifier: Intended Audience :: System Administrators
Classifier: License :: OSI Approved :: MIT License
Classifier: Operating System :: Unix
Classifier: Operating System :: POSIX :: Linux
Classifier: Environment :: Console
Classifier: Environment :: MacOS X
Classifier: Topic :: Software Development :: Libraries :: Python Modules
Classifier: Topic :: Internet
License-File: LICENSE
Summary: A TOML library for python implemented in rust.
Author-email: Samuel Colvin <s@muelcolvin.com>
License: MIT
Requires-Python: >=3.10
Project-URL: Homepage, https://github.com/samuelcolvin/rtoml
Project-URL: Funding, https://github.com/sponsors/samuelcolvin
Project-URL: Source, https://github.com/samuelcolvin/rtoml
